marzpay/__init__.py
marzpay/marzpay.py
marzpay/classes/__init__.py
marzpay/classes/accounts.py
marzpay/classes/balance.py
marzpay/classes/collections.py
marzpay/classes/disbursements.py
marzpay/classes/phone_verification.py
marzpay/classes/services.py
marzpay/classes/transactions.py
marzpay/classes/webhooks.py
marzpay/errors/__init__.py
marzpay/errors/marzpay_error.py
marzpay/utils/__init__.py
marzpay/utils/callback_handler.py
marzpay/utils/general_utils.py
marzpay/utils/phone_number_utils.py
marzpay_python-1.0.0.dist-info/licenses/LICENSE
marzpay_python-1.0.0.dist-info/METADATA
marzpay_python-1.0.0.dist-info/WHEEL
marzpay_python-1.0.0.dist-info/top_level.txt
marzpay_python-1.0.0.dist-info/RECORD
