Metadata-Version: 2.4
Name: marzpay-python
Version: 1.0.0
Summary: Official Python SDK for MarzPay - Mobile Money Payment Platform for Uganda
Author-email: MarzPay Team <dev@wearemarz.com>
Maintainer-email: MarzPay Team <dev@wearemarz.com>
License-Expression: MIT
Project-URL: Homepage, https://github.com/Katznicho/marzpay-python
Project-URL: Documentation, https://wallet.wearemarz.com/documentation
Project-URL: Repository, https://github.com/Katznicho/marzpay-python
Project-URL: Bug Tracker, https://github.com/Katznicho/marzpay-python/issues
Keywords: marzpay,mobile-money,uganda,payments,collections,disbursements,api,sdk
Classifier: Development Status :: 5 - Production/Stable
Classifier: Intended Audience :: Developers
Classifier: Operating System :: OS Independent
Classifier: Programming Language :: Python :: 3
Classifier: Programming Language :: Python :: 3.8
Classifier: Programming Language :: Python :: 3.9
Classifier: Programming Language :: Python :: 3.10
Classifier: Programming Language :: Python :: 3.11
Classifier: Programming Language :: Python :: 3.12
Classifier: Topic :: Software Development :: Libraries :: Python Modules
Classifier: Topic :: Office/Business :: Financial
Requires-Python: >=3.8
License-File: LICENSE
Requires-Dist: requests>=2.25.0
Requires-Dist: urllib3>=1.26.0
Provides-Extra: dev
Requires-Dist: pytest>=6.0; extra == "dev"
Requires-Dist: pytest-cov>=2.0; extra == "dev"
Requires-Dist: black>=21.0; extra == "dev"
Requires-Dist: flake8>=3.8; extra == "dev"
Requires-Dist: mypy>=0.800; extra == "dev"
Provides-Extra: docs
Requires-Dist: sphinx>=4.0; extra == "docs"
Requires-Dist: sphinx-rtd-theme>=0.5; extra == "docs"
Dynamic: license-file
